pydatadeck/__init__.py
pydatadeck/datasource/__init__.py
pydatadeck/datasource/aggregation.py
pydatadeck/datasource/datetime_util.py
pydatadeck/datasource/errors.py
pydatadeck/datasource/filter.py
pydatadeck/datasource/format.py
pydatadeck/datasource/logging.py
pydatadeck/datasource/operators.py
pydatadeck/datasource/service_factory.py
pydatadeck/datasource/translation.py
pydatadeck/datasource/locales/en_US/LC_MESSAGES/errors.mo
pydatadeck/datasource/locales/en_US/LC_MESSAGES/errors.po
pydatadeck/datasource/locales/ja_JP/LC_MESSAGES/errors.mo
pydatadeck/datasource/locales/ja_JP/LC_MESSAGES/errors.po
pydatadeck/datasource/locales/zh_CN/LC_MESSAGES/errors.mo
pydatadeck/datasource/locales/zh_CN/LC_MESSAGES/errors.po
pydatadeck-0.9.31.dist-info/METADATA
pydatadeck-0.9.31.dist-info/WHEEL
pydatadeck-0.9.31.dist-info/top_level.txt
pydatadeck-0.9.31.dist-info/RECORD
