Metadata-Version: 2.1
Name: pydatadeck
Version: 0.9.31
Summary: Python SDK for Datadeck
Home-page: https://www.datadeck.com
Author: Datadeck Dev
Author-email: datadeck_dev@ptmind.com
License: MIT
Keywords: datadeck
Platform: UNKNOWN
Classifier: Development Status :: 4 - Beta
Classifier: Programming Language :: Python :: 3.7
Requires-Dist: flask (==1.0.2)
Requires-Dist: pyyaml (==3.13)
Requires-Dist: pytz (==2018.9)
